iqEditors/__init__.py
iqEditors/commons.py
iqEditors/noteEditor.py
iqEditors/providers.py
iqEditors/simpleEditor.py
iqEditors/styles.py
iqEditors-2.0.2.dist-info/LICENSE
iqEditors-2.0.2.dist-info/METADATA
iqEditors-2.0.2.dist-info/WHEEL
iqEditors-2.0.2.dist-info/top_level.txt
iqEditors-2.0.2.dist-info/RECORD
