Metadata-Version: 2.1
Name: iqEditors
Version: 2.0.2
Summary: Основанные на QTextEdit продвинутые текстовые редакторы для PyQt5
Home-page: https://gitflic.ru/project/iqstudio/iq-editors
Author: Alexander N Khilchenko
Author-email: khan.programming@mail.ru
License: UNKNOWN
Platform: UNKNOWN
Classifier: License :: OSI Approved :: GNU General Public License v3 (GPLv3)
Classifier: Natural Language :: Russian
Classifier: Operating System :: MacOS :: MacOS X
Classifier: Operating System :: POSIX
Classifier: Operating System :: POSIX :: BSD
Classifier: Operating System :: POSIX :: Linux
Classifier: Operating System :: Microsoft :: Windows
Classifier: Environment :: X11 Applications :: Qt
Classifier: Environment :: Other Environment
Classifier: Topic :: Desktop Environment :: Gnome
Classifier: Topic :: Desktop Environment :: K Desktop Environment (KDE)
Classifier: Topic :: Desktop Environment
Classifier: Programming Language :: Python
Classifier: Programming Language :: Python :: 3
Classifier: Programming Language :: Python :: 3 :: Only
Classifier: Programming Language :: Python :: 3.7
Classifier: Programming Language :: Python :: 3.8
Classifier: Programming Language :: Python :: 3.9
Classifier: Programming Language :: Python :: 3.10
Classifier: Programming Language :: Python :: Implementation :: CPython
Classifier: Programming Language :: Python :: Implementation :: PyPy
Classifier: Typing :: Typed
Requires-Python: >=3.6
License-File: LICENSE
Requires-Dist: pygments
Requires-Dist: pyenchant
